{
    "slug": "homestay-bu-maesaroh",
    "name": "Homestay Bu Maesaroh",
    "excerpt": "Homestay nyaman dengan fasilitas lengkap di Desa Wisata Bantaragung.",
    "description": "Homestay Bu Maesaroh menyediakan pengalaman tinggal bersama warga lokal dengan suasana pedesaan yang asri. Dilengkapi dengan berbagai fasilitas untuk kenyamanan Anda.",
    "cover": "bdb/homestay/homestay-bu-maesaroh/cover.jpg",
    "gallery": [
        "bdb/homestay/homestay-bu-maesaroh/01.jpg",
        "bdb/homestay/homestay-bu-maesaroh/02.jpg"
    ],
    "capacity": "4 orang",
    "address": "Desa Wisata Bantaragung",
    "facilities": [
        "Kamar Mandi Pribadi",
        "Kipas Angin",
        "Perlengkapan Mandi",
        "Sarapan Pagi"
    ],
    "contact": {
        "whatsapp": "6281384996974"
    }
}